async_poe_client/__init__.py
async_poe_client/client.py
async_poe_client/type.py
async_poe_client/util.py
async_poe_client-0.3.7.dist-info/METADATA
async_poe_client-0.3.7.dist-info/WHEEL
async_poe_client-0.3.7.dist-info/RECORD
