Metadata-Version: 2.1
Name: async-poe-client
Version: 0.3.7
Summary: A stable, fast and convenient async client for poe.com
Author: canxin
Author-email: 1969730106@qq.com
Requires-Python: >=3.7,<4.0
Classifier: Programming Language :: Python :: 3
Classifier: Programming Language :: Python :: 3.7
Classifier: Programming Language :: Python :: 3.8
Classifier: Programming Language :: Python :: 3.9
Classifier: Programming Language :: Python :: 3.10
Classifier: Programming Language :: Python :: 3.11
Requires-Dist: aiohttp (>=3.8.5,<4.0.0)
Requires-Dist: aiohttp-socks (>=0.8.0,<0.9.0)
Requires-Dist: loguru (>=0.7.0,<0.8.0)
Requires-Dist: pydantic (>=1.10.12,<2.0.0)
